odd_great_expectations/__init__.py
odd_great_expectations/action.py
odd_great_expectations/dataset/__init__.py
odd_great_expectations/dataset/file.py
odd_great_expectations/dataset/get_dataset.py
odd_great_expectations/dataset/sql_table.py
odd_great_expectations/logger.py
odd_great_expectations/mapper.py
odd_great_expectations-0.2.5.dist-info/LICENSE
odd_great_expectations-0.2.5.dist-info/METADATA
odd_great_expectations-0.2.5.dist-info/WHEEL
odd_great_expectations-0.2.5.dist-info/RECORD
