Metadata-Version: 2.1
Name: odd-great-expectations
Version: 0.2.5
Summary: OpenDataDiscovery Action for Great Expectations
License: Apache-2.0
Keywords: Open Data Discovery,Great Expectations,Metadata,Data Discovery,Data Observability
Author: Pavel Makarichev
Author-email: vixtir90@gmail.com
Requires-Python: >=3.9,<4.0
Classifier: License :: OSI Approved :: Apache Software License
Classifier: Programming Language :: Python :: 3
Classifier: Programming Language :: Python :: 3.9
Classifier: Programming Language :: Python :: 3.10
Classifier: Programming Language :: Python :: 3.11
Requires-Dist: funcy (>=2.0,<3.0)
Requires-Dist: great-expectations (==0.18.21)
Requires-Dist: loguru (>=0.7.2,<0.8.0)
Requires-Dist: odd-models (>=2.0.50,<3.0.0)
Requires-Dist: oddrn-generator (>=0.1.103,<0.2.0)
Requires-Dist: psycopg2-binary (>=2.9.5,<3.0.0)
Requires-Dist: sqlalchemy (>=2.0.35,<3.0.0)
